django_oemof/__init__.py
django_oemof/admin.py
django_oemof/apps.py
django_oemof/hooks.py
django_oemof/management/__init__.py
django_oemof/management/commands/__init__.py
django_oemof/management/commands/add_static_results.py
django_oemof/migrations/0001_initial.py
django_oemof/migrations/0002_simulation.py
django_oemof/migrations/0003_result.py
django_oemof/migrations/0004_alter_simulation_dataset.py
django_oemof/migrations/0005_alter_result_name.py
django_oemof/migrations/0006_oemofdataset_meta_results.py
django_oemof/migrations/__init__.py
django_oemof/models.py
django_oemof/results.py
django_oemof/serializers.py
django_oemof/settings.py
django_oemof/simulation.py
django_oemof/standalone.py
django_oemof/static/django_oemof/js/simulation.js
django_oemof/templates/django_oemof/flows.html
django_oemof/tests/__init__.py
django_oemof/tests/settings.py
django_oemof/tests/test_data/oemof/dispatch/data/elements/bus.csv
django_oemof/tests/test_data/oemof/dispatch/data/elements/dispatchable.csv
django_oemof/tests/test_data/oemof/dispatch/data/elements/link.csv
django_oemof/tests/test_data/oemof/dispatch/data/elements/load.csv
django_oemof/tests/test_data/oemof/dispatch/data/elements/storage.csv
django_oemof/tests/test_data/oemof/dispatch/data/elements/volatile.csv
django_oemof/tests/test_data/oemof/dispatch/data/sequences/load_profile.csv
django_oemof/tests/test_data/oemof/dispatch/data/sequences/volatile_profile.csv
django_oemof/tests/test_data/oemof/dispatch/datapackage.json
django_oemof/tests/test_data/oemof/test_scenario/.snakemake_timestamp
django_oemof/tests/test_data/oemof/test_scenario/additional_scalars.csv
django_oemof/tests/test_data/oemof/test_scenario/data/elements/biomass-demand.csv
django_oemof/tests/test_data/oemof/test_scenario/data/elements/biomass-fermenter.csv
django_oemof/tests/test_data/oemof/test_scenario/data/elements/biomass-import.csv
django_oemof/tests/test_data/oemof/test_scenario/data/elements/bus.csv
django_oemof-2.1.0.dist-info/LICENSE
django_oemof-2.1.0.dist-info/METADATA
django_oemof-2.1.0.dist-info/WHEEL
django_oemof-2.1.0.dist-info/RECORD
