Metadata-Version: 2.3
Name: django-oemof
Version: 2.1.0
Summary: Django application to run oemof
License: AGPL-3.0
Author: Hendrik Huyskens
Author-email: hendrik.huyskens@rl-institut.de
Requires-Python: >=3.9,<4.0
Classifier: License :: OSI Approved :: GNU Affero General Public License v3
Classifier: Programming Language :: Python :: 3
Classifier: Programming Language :: Python :: 3.9
Classifier: Programming Language :: Python :: 3.10
Classifier: Programming Language :: Python :: 3.11
Classifier: Programming Language :: Python :: 3.12
Classifier: Programming Language :: Python :: 3.13
Requires-Dist: celery (>=5.1.2,<6.0.0)
Requires-Dist: django-environ (>0.10.0)
Requires-Dist: djangorestframework (>=3.14.0,<4.0.0)
Requires-Dist: numpy (<2.0)
Requires-Dist: pandas (>2.0)
Requires-Dist: psycopg2-binary (>=2.9.10,<3.0.0)
